dbworkload/__init__.py
dbworkload/cli/dep.py
dbworkload/cli/main.py
dbworkload/cli/util.py
dbworkload/models/convert.py
dbworkload/models/prompts.py
dbworkload/models/run.py
dbworkload/models/util.py
dbworkload/templates/stub.j2
dbworkload/utils/common.py
dbworkload/utils/simplefaker.py
dbworkload-0.11.0.dist-info/METADATA
dbworkload-0.11.0.dist-info/WHEEL
dbworkload-0.11.0.dist-info/entry_points.txt
dbworkload-0.11.0.dist-info/licenses/LICENSE
dbworkload-0.11.0.dist-info/RECORD
