Metadata-Version: 2.4
Name: dbworkload
Version: 0.11.0
Summary: Workload framework
License: GPLv3+
License-File: LICENSE
Author: Fabio Ghirardello
Requires-Python: >=3.11,<4.0
Classifier: License :: OSI Approved :: GNU General Public License v3 or later (GPLv3+)
Classifier: License :: Other/Proprietary License
Classifier: Operating System :: OS Independent
Classifier: Programming Language :: Python :: 3
Classifier: Programming Language :: Python :: 3.11
Classifier: Programming Language :: Python :: 3.12
Classifier: Programming Language :: Python :: 3.13
Classifier: Programming Language :: Python :: 3.14
Provides-Extra: all
Provides-Extra: cassandra
Provides-Extra: convert
Provides-Extra: mariadb
Provides-Extra: mongo
Provides-Extra: mysql
Provides-Extra: odbc
Provides-Extra: oracle
Provides-Extra: pinecone
Provides-Extra: postgres
Provides-Extra: spanner
Requires-Dist: cassandra-driver ; extra == "all" or extra == "cassandra"
Requires-Dist: fastembed (>=0.7.3,<0.8.0) ; extra == "convert"
Requires-Dist: google-cloud-spanner ; extra == "all" or extra == "spanner"
Requires-Dist: jinja2
Requires-Dist: langchain-core (>=1.0.5,<2.0.0) ; extra == "convert"
Requires-Dist: langchain-ollama (>=1.0.0,<2.0.0) ; extra == "convert"
Requires-Dist: langchain-openai (>=1.0.2,<2.0.0) ; extra == "convert"
Requires-Dist: langgraph (>=1.0.3,<2.0.0) ; extra == "convert"
Requires-Dist: mariadb ; extra == "all" or extra == "mariadb"
Requires-Dist: mysql-connector-python ; extra == "all" or extra == "mysql"
Requires-Dist: numpy
Requires-Dist: openai (>=2.8.0,<3.0.0) ; extra == "convert"
Requires-Dist: oracledb ; extra == "all" or extra == "oracle"
Requires-Dist: pandas
Requires-Dist: pgvector (>=0.4.1,<0.5.0) ; extra == "convert"
Requires-Dist: pinecone[asyncio,grpc] (>=8.0.0,<9.0.0) ; extra == "all" or extra == "pinecone"
Requires-Dist: plotext
Requires-Dist: plotly
Requires-Dist: prometheus-client
Requires-Dist: psutil (>=7.0.0,<8.0.0)
Requires-Dist: psycopg ; extra == "all" or extra == "postgres"
Requires-Dist: psycopg-binary ; extra == "all" or extra == "postgres"
Requires-Dist: pymongo ; extra == "all" or extra == "mongo"
Requires-Dist: pyodbc ; extra == "all" or extra == "odbc"
Requires-Dist: pytdigest
Requires-Dist: pyyaml
Requires-Dist: sentence-transformers ; extra == "pinecone"
Requires-Dist: sqlparse
Requires-Dist: tabulate
Requires-Dist: typer[all]
Project-URL: Homepage, https://dbworkload.github.io/dbworkload/
Project-URL: Repository, https://github.com/dbworkload/dbworkload
